README.txt
setup.py
docs/HISTORY.txt
docs/INSTALL.txt
docs/LICENSE.GPL
docs/LICENSE.txt
wildcard/__init__.py
wildcard.templatedviews.egg-info/PKG-INFO
wildcard.templatedviews.egg-info/SOURCES.txt
wildcard.templatedviews.egg-info/dependency_links.txt
wildcard.templatedviews.egg-info/entry_points.txt
wildcard.templatedviews.egg-info/namespace_packages.txt
wildcard.templatedviews.egg-info/not-zip-safe
wildcard.templatedviews.egg-info/requires.txt
wildcard.templatedviews.egg-info/top_level.txt
wildcard/templatedviews/__init__.py
wildcard/templatedviews/base-template.pt
wildcard/templatedviews/browser.py
wildcard/templatedviews/configure.zcml
wildcard/templatedviews/events.py
wildcard/templatedviews/interfaces.py
wildcard/templatedviews/referenced-template.pt
wildcard/templatedviews/settings.py
wildcard/templatedviews/setuphandlers.py
wildcard/templatedviews/tests.py
wildcard/templatedviews/utils.py
wildcard/templatedviews/vocabularies.py
wildcard/templatedviews/profiles/default/actions.xml
wildcard/templatedviews/profiles/default/browserlayer.xml
wildcard/templatedviews/profiles/default/import_steps.xml