Metadata-Version: 1.0
Name: wildcard.templatedviews
Version: 1.0b3
Summary: Provide templated views with schema settings associated with them.
Home-page: http://svn.plone.org/svn/collective/
Author: Nathan Van Gheem
Author-email: vangheem@gmail.com
License: GPL
Keywords: plone template views settings
Platform: UNKNOWN
Classifier: Framework :: Plone
Classifier: Programming Language :: Python
